{
  "tabPane": [
    {
      "title": "SmartDashboard",
      "autoPopulate": true,
      "autoPopulatePrefix": "SmartDashboard/",
      "widgetPane": {
        "gridSize": 24.0,
        "showGrid": true,
        "hgap": 16.0,
        "vgap": 16.0,
        "titleType": 0,
        "tiles": {
          "0,0": {
            "size": [
              3,
              2
            ],
            "content": {
              "_type": "Text View",
              "_source0": "network_table:///SmartDashboard/limelight_PipelineName",
              "_title": "PIPELINE"
            }
          },
          "3,0": {
            "size": [
              2,
              2
            ],
            "content": {
              "_type": "Text View",
              "_source0": "network_table:///SmartDashboard/Roll",
              "_title": "Roll"
            }
          },
          "0,2": {
            "size": [
              7,
              3
            ],
            "content": {
              "_type": "Number Slider",
              "_source0": "network_table:///SmartDashboard/Extend Speed",
              "_title": "Extend Speed",
              "Slider Settings/Min": 0.0,
              "Slider Settings/Max": 1.0,
              "Slider Settings/Block increment": 0.0625,
              "Visuals/Display value": true
            }
          },
          "5,0": {
            "size": [
              4,
              2
            ],
            "content": {
              "_type": "Text View",
              "_source0": "network_table:///SmartDashboard/Drive Mode",
              "_title": "Drive Mode"
            }
          },
          "9,0": {
            "size": [
              5,
              2
            ],
            "content": {
              "_type": "Text View",
              "_source0": "network_table:///SmartDashboard/Drive Control",
              "_title": "Drive Control"
            }
          },
          "7,2": {
            "size": [
              7,
              3
            ],
            "content": {
              "_type": "Number Slider",
              "_source0": "network_table:///SmartDashboard/Drive Speed",
              "_title": "Drive Speed",
              "Slider Settings/Min": 0.0,
              "Slider Settings/Max": 1.0,
              "Slider Settings/Block increment": 0.0625,
              "Visuals/Display value": true
            }
          },
          "14,0": {
            "size": [
              2,
              4
            ],
            "content": {
              "_type": "Boolean Box",
              "_source0": "network_table:///SmartDashboard/LEDS",
              "_title": "LEDS",
              "Colors/Color when true": "#7CFC00FF",
              "Colors/Color when false": "#8B0000FF"
            }
          },
          "8,5": {
            "size": [
              6,
              4
            ],
            "content": {
              "_type": "ComboBox Chooser",
              "_source0": "network_table:///SmartDashboard/SendableChooser[0]",
              "_title": "AUTON MODE CHOOSER"
            }
          },
          "0,5": {
            "size": [
              4,
              4
            ],
            "content": {
              "_type": "Simple Dial",
              "_source0": "network_table:///SmartDashboard/Storage Pressure",
              "_title": "Storage Pressure",
              "Range/Min": 0.0,
              "Range/Max": 130.0,
              "Visuals/Show value": true
            }
          },
          "16,0": {
            "size": [
              4,
              2
            ],
            "content": {
              "_type": "Text View",
              "_source0": "network_table:///SmartDashboard/Valid Target",
              "_title": "Valid Target"
            }
          },
          "14,6": {
            "size": [
              5,
              2
            ],
            "content": {
              "_type": "Text View",
              "_source0": "network_table:///SmartDashboard/Arm Encoder",
              "_title": "Arm Encoder"
            }
          },
          "14,4": {
            "size": [
              5,
              2
            ],
            "content": {
              "_type": "Text View",
              "_source0": "network_table:///SmartDashboard/Drive Encoder",
              "_title": "Drive Encoder"
            }
          },
          "19,4": {
            "size": [
              4,
              2
            ],
            "content": {
              "_type": "Text View",
              "_source0": "network_table:///SmartDashboard/Ex \u0026 Rt Encoder",
              "_title": "Ex \u0026 Rt Encoder"
            }
          },
          "16,2": {
            "size": [
              4,
              2
            ],
            "content": {
              "_type": "Text View",
              "_source0": "network_table:///SmartDashboard/Driver Control",
              "_title": "Driver Control"
            }
          },
          "20,6": {
            "size": [
              4,
              2
            ],
            "content": {
              "_type": "Text View",
              "_source0": "network_table:///SmartDashboard/EncoderValue",
              "_title": "EncoderValue"
            }
          },
          "4,5": {
            "size": [
              4,
              4
            ],
            "content": {
              "_type": "Simple Dial",
              "_source0": "network_table:///SmartDashboard/Working Pressure",
              "_title": "Working Pressure",
              "Range/Min": 0.0,
              "Range/Max": 70.0,
              "Visuals/Show value": true
            }
          }
        }
      }
    }
  ],
  "windowGeometry": {
    "x": 0.0,
    "y": 0.0,
    "width": 1280.0,
    "height": 480.0
  }
}